odoo/addons/account_analytic_distribution/README.rst
odoo/addons/account_analytic_distribution/__init__.py
odoo/addons/account_analytic_distribution/__manifest__.py
odoo/addons/account_analytic_distribution/i18n/account_analytic_distribution.pot
odoo/addons/account_analytic_distribution/i18n/ar.po
odoo/addons/account_analytic_distribution/i18n/bs.po
odoo/addons/account_analytic_distribution/i18n/ca.po
odoo/addons/account_analytic_distribution/i18n/cs.po
odoo/addons/account_analytic_distribution/i18n/cs_CZ.po
odoo/addons/account_analytic_distribution/i18n/de.po
odoo/addons/account_analytic_distribution/i18n/en_GB.po
odoo/addons/account_analytic_distribution/i18n/es.po
odoo/addons/account_analytic_distribution/i18n/es_CR.po
odoo/addons/account_analytic_distribution/i18n/es_EC.po
odoo/addons/account_analytic_distribution/i18n/es_MX.po
odoo/addons/account_analytic_distribution/i18n/es_PA.po
odoo/addons/account_analytic_distribution/i18n/es_VE.po
odoo/addons/account_analytic_distribution/i18n/et.po
odoo/addons/account_analytic_distribution/i18n/fr.po
odoo/addons/account_analytic_distribution/i18n/fr_CH.po
odoo/addons/account_analytic_distribution/i18n/gl.po
odoo/addons/account_analytic_distribution/i18n/hr.po
odoo/addons/account_analytic_distribution/i18n/hr_HR.po
odoo/addons/account_analytic_distribution/i18n/hu.po
odoo/addons/account_analytic_distribution/i18n/it.po
odoo/addons/account_analytic_distribution/i18n/ja.po
odoo/addons/account_analytic_distribution/i18n/lt.po
odoo/addons/account_analytic_distribution/i18n/mk.po
odoo/addons/account_analytic_distribution/i18n/mn.po
odoo/addons/account_analytic_distribution/i18n/nb.po
odoo/addons/account_analytic_distribution/i18n/nl.po
odoo/addons/account_analytic_distribution/i18n/nl_BE.po
odoo/addons/account_analytic_distribution/i18n/nl_NL.po
odoo/addons/account_analytic_distribution/i18n/pl.po
odoo/addons/account_analytic_distribution/i18n/pt.po
odoo/addons/account_analytic_distribution/i18n/pt_BR.po
odoo11_addon_account_analytic_distribution-11.0.1.0.0.99.dev14.dist-info/METADATA
odoo11_addon_account_analytic_distribution-11.0.1.0.0.99.dev14.dist-info/WHEEL
odoo11_addon_account_analytic_distribution-11.0.1.0.0.99.dev14.dist-info/top_level.txt
odoo11_addon_account_analytic_distribution-11.0.1.0.0.99.dev14.dist-info/RECORD
